HISTORY.rst
LICENSE
MANIFEST.in
README.rst
setup.cfg
setup.py
tox.ini
actors/__init__.py
actors/actor.py
actors/context.py
actors/future.py
actors/ref.py
actors/system.py
actors/utils.py
actors.egg-info/PKG-INFO
actors.egg-info/SOURCES.txt
actors.egg-info/dependency_links.txt
actors.egg-info/requires.txt
actors.egg-info/top_level.txt
actors/internal/__init__.py
actors/internal/cell.py
actors/internal/dispatcher.py
actors/internal/executor.py
actors/internal/factory.py
actors/internal/mailbox.py
actors/internal/messages.py
docs/conf.py
docs/index.rst
examples/greeter.py
examples/supervision_example.py
tests/__init__.py
tests/mock_compat.py
tests/test_cell.py
tests/test_dispatcher.py
tests/test_future.py
tests/test_mailbox.py
tests/test_restart.py
tests/test_supervision.py
tests/test_terminate.py
tests/integration/__init__.py
tests/integration/test_executor.py
tests/integration/test_factory.py