Metadata-Version: 1.1
Name: actors
Version: 0.5.0b1
Summary: Lightweight actor framework with supervision
Home-page: https://github.com/tamland/python-actors/
Author: Thomas Amland
Author-email: thomas.amland@googlemail.com
License: Apache License 2.0
Keywords: actors,reactive,concurrent,threading,message passing,asynchronous
Platform: UNKNOWN
Classifier: Development Status :: 3 - Alpha
Classifier: Intended Audience :: Developers
Classifier: License :: OSI Approved :: Apache Software License
Classifier: Programming Language :: Python :: 2
Classifier: Programming Language :: Python :: 2.6
Classifier: Programming Language :: Python :: 2.7
Classifier: Programming Language :: Python :: 3
Classifier: Programming Language :: Python :: 3.3
Classifier: Programming Language :: Python :: 3.4
Classifier: Programming Language :: Python :: 3.5
Classifier: Programming Language :: Python :: Implementation :: CPython
Classifier: Programming Language :: Python :: Implementation :: PyPy 
Classifier: Topic :: Software Development :: Libraries
